[
  {
    "deck_name": "Blue Doffy",
    "author": "Happy",
    "date": "2/24/2025",
    "country": "JP",
    "tournament": "3v3",
    "placement": "1st Place",
    "host": "Bandai Winter Cup",
    "decklist": {
      "OP01-060": 1,
      "ST03-005": 3,
      "ST03-004": 3,
      "OP01-077": 4,
      "OP03-044": 1,
      "OP06-047": 2,
      "EB01-023": 4,
      "OP07-040": 4,
      "OP07-045": 4,
      "OP07-046": 4,
      "OP08-047": 1,
      "ST17-002": 4,
      "ST17-003": 4,
      "ST17-004": 4,
      "ST17-005": 4,
      "OP06-058": 2,
      "OP07-057": 2
    }
  },
  {
    "deck_name": "Green Purple Luffy",
    "author": "Esu",
    "date": "2/24/2025",
    "country": "JP",
    "tournament": "3v3",
    "placement": "1st Place",
    "host": "Bandai Winter Cup",
    "decklist": {
      "EB02-010": 1,
      "OP05-070": 2,
      "EB02-035": 4,
      "EB02-036": 2,
      "EB02-061": 4,
      "OP07-064": 4,
      "ST18-001": 4,
      "ST18-004": 4,
      "OP09-063": 2,
      "EB02-017": 4,
      "EB02-019": 2,
      "OP03-072": 2,
      "OP05-076": 4,
      "EB02-041": 4,
      "OP09-078": 4,
      "OP08-036": 4
    }
  },
  {
    "deck_name": "Teach",
    "author": "Yuta",
    "date": "2/24/2025",
    "country": "JP",
    "tournament": "3v3",
    "placement": "1st Place",
    "host": "Bandai Winter Cup",
    "decklist": {
      "OP09-081": 1,
      "OP09-083": 4,
      "OP09-086": 4,
      "OP09-088": 3,
      "OP09-089": 4,
      "OP09-090": 4,
      "OP09-091": 2,
      "OP09-093": 4,
      "OP09-095": 4,
      "OP10-082": 4,
      "EB01-051": 4,
      "OP09-096": 4,
      "OP09-098": 2,
      "OP09-099": 4,
      "OP10-098": 3
    }
  },
  {
    "deck_name": "Blue Doffy",
    "author": "Ichamon",
    "date": "2/24/2025",
    "country": "JP",
    "tournament": "3v3",
    "placement": "2nd Place",
    "host": "Bandai Winter Cup",
    "decklist": {
      "OP01-060": 1,
      "ST03-005": 4,
      "ST03-004": 3,
      "OP01-077": 4,
      "OP06-047": 2,
      "EB01-023": 4,
      "OP07-040": 4,
      "OP07-045": 4,
      "OP07-046": 4,
      "OP08-047": 2,
      "ST17-002": 4,
      "ST17-003": 4,
      "ST17-004": 4,
      "ST17-005": 4,
      "OP06-058": 1,
      "OP07-057": 2
    }
  },
  {
    "deck_name": "Green Purple Luffy",
    "author": "Pesu",
    "date": "2/24/2025",
    "country": "JP",
    "tournament": "3v3(7-5)",
    "placement": "2nd Place",
    "host": "Bandai Winter Cup",
    "decklist": {
      "EB02-010": 1,
      "EB02-035": 4,
      "EB02-037": 2,
      "EB02-061": 4,
      "OP07-064": 4,
      "OP07-066": 2,
      "ST18-001": 4,
      "ST18-004": 4,
      "EB02-017": 4,
      "EB02-019": 4,
      "OP03-072": 2,
      "OP05-076": 4,
      "EB02-041": 4,
      "OP09-078": 4,
      "OP08-036": 4
    }
  },
  {
    "deck_name": "BY Luffy",
    "author": "Shingetsu",
    "date": "2/24/2025",
    "country": "JP",
    "tournament": "3v3",
    "placement": "2nd Place",
    "host": "Bandai Winter Cup",
    "decklist": {
      "ST13-003": 1,
      "OP06-106": 4,
      "ST13-007": 4,
      "ST13-008": 2,
      "ST13-013": 4,
      "ST13-014": 4,
      "ST13-015": 4,
      "EB01-056": 4,
      "OP07-109": 4,
      "OP10-103": 2,
      "OP02-096": 3,
      "OP04-083": 4,
      "OP06-086": 4,
      "ST13-019": 4,
      "EB01-059": 2,
      "OP02-117": 1
    }
  },
  {
    "deck_name": "Vegapunk",
    "author": "Hikaru",
    "date": "2/24/2025",
    "country": "JP",
    "tournament": "3v3(10-1)",
    "placement": "Top-4",
    "host": "Bandai Winter Cup",
    "decklist": {
      "OP07-097": 1,
      "EB02-056": 4,
      "OP07-100": 4,
      "OP07-101": 4,
      "OP07-105": 4,
      "OP07-107": 2,
      "OP07-109": 4,
      "OP07-111": 4,
      "OP07-098": 4,
      "OP08-106": 4,
      "OP10-112": 3,
      "EB01-059": 1,
      "OP07-114": 4,
      "OP07-115": 4,
      "OP09-117": 4
    }
  },
  {
    "deck_name": "Moria",
    "author": "Sanma",
    "date": "2/24/2025",
    "country": "JP",
    "tournament": "3v3(8-2)",
    "placement": "Top-8",
    "host": "Bandai Winter Cup",
    "decklist": {
      "OP06-080": 1,
      "OP02-096": 2,
      "ST06-006": 2,
      "ST06-008": 4,
      "ST06-010": 2,
      "OP02-106": 4,
      "OP03-089": 4,
      "OP05-091": 4,
      "OP06-081": 4,
      "OP06-086": 4,
      "OP06-090": 2,
      "OP06-091": 4,
      "OP06-093": 4,
      "EB01-046": 4,
      "EB02-044": 2,
      "OP02-117": 4
    }
  },
  {
    "deck_name": "Green Purple Luffy",
    "author": "Ayakana",
    "date": "2/24/2025",
    "country": "JP",
    "tournament": "Shop Event(8-0)",
    "placement": "1st Place",
    "host": "Emperor Cup",
    "decklist": {
      "EB02-010": 1,
      "OP05-070": 4,
      "EB02-035": 4,
      "EB02-036": 2,
      "EB02-037": 2,
      "EB02-061": 4,
      "OP07-064": 4,
      "ST18-001": 4,
      "ST18-004": 4,
      "EB02-017": 4,
      "EB02-019": 4,
      "OP05-076": 2,
      "EB02-041": 4,
      "OP09-078": 4,
      "OP08-036": 4
    }
  },
  {
    "deck_name": "Green Bonney",
    "author": "Raphterra",
    "date": "2/23/2025",
    "country": "PH",
    "tournament": "Flagship",
    "placement": "1st Place",
    "host": "Block 101 Hobbies",
    "decklist": {
      "OP07-019": 1,
      "OP01-039": 3,
      "OP01-051": 4,
      "ST02-007": 4,
      "ST02-008": 3,
      "OP01-052": 1,
      "OP04-031": 2,
      "OP05-030": 4,
      "OP06-035": 3,
      "EB01-012": 4,
      "EB01-015": 4,
      "ST16-004": 3,
      "OP07-021": 2,
      "OP08-023": 4,
      "OP10-030": 3,
      "OP10-032": 4,
      "OP05-037": 2
    }
  },
  {
    "deck_name": "Blue Doffy",
    "author": "Silvia",
    "date": "2/23/2025",
    "country": "JP",
    "tournament": "Flagship",
    "placement": "1st Place",
    "host": "gamekan_beat(32)",
    "decklist": {
      "OP01-060": 1,
      "ST03-005": 3,
      "ST03-004": 1,
      "OP01-077": 4,
      "OP03-044": 1,
      "OP06-047": 3,
      "EB01-023": 4,
      "OP07-040": 4,
      "OP07-045": 4,
      "OP07-046": 4,
      "OP08-047": 2,
      "ST17-002": 4,
      "ST17-003": 4,
      "ST17-004": 4,
      "ST17-005": 4,
      "OP06-058": 3,
      "OP07-057": 1
    }
  },
  {
    "deck_name": "Green Purple Luffy",
    "author": "Mario",
    "date": "2/23/2025",
    "country": "JP",
    "tournament": "3v3(6-2)",
    "placement": "1st Place",
    "host": "Hacchi CS(96)",
    "decklist": {
      "EB02-010": 1,
      "OP05-070": 3,
      "EB02-035": 4,
      "EB02-036": 4,
      "EB02-061": 4,
      "OP07-064": 4,
      "ST18-001": 4,
      "ST18-004": 4,
      "EB02-017": 4,
      "EB02-019": 4,
      "OP03-072": 1,
      "OP05-076": 3,
      "EB02-041": 4,
      "OP09-078": 4,
      "OP08-036": 3
    }
  },
  {
    "deck_name": "Blue Doffy",
    "author": "Aire",
    "date": "2/23/2025",
    "country": "JP",
    "tournament": "3v3(5-3)",
    "placement": "1st Place",
    "host": "Hacchi CS(96)",
    "decklist": {
      "OP01-060": 1,
      "ST03-005": 3,
      "ST03-004": 3,
      "OP01-077": 4,
      "OP06-047": 2,
      "EB01-023": 4,
      "OP07-040": 4,
      "OP07-045": 4,
      "OP07-046": 4,
      "OP08-047": 2,
      "ST17-002": 4,
      "ST17-003": 4,
      "ST17-004": 4,
      "ST17-005": 4,
      "OP06-058": 2,
      "OP07-057": 2
    }
  },
  {
    "deck_name": "Black Lucci",
    "author": "RKT",
    "date": "2/23/2025",
    "country": "JP",
    "tournament": "3v3(6-2)",
    "placement": "1st Place",
    "host": "Hacchi CS(96)",
    "decklist": {
      "OP07-079": 1,
      "ST06-008": 1,
      "ST06-010": 1,
      "OP02-106": 4,
      "OP03-080": 3,
      "OP03-081": 4,
      "OP03-086": 4,
      "OP04-083": 1,
      "OP05-091": 4,
      "OP05-093": 4,
      "OP06-086": 4,
      "EB01-043": 2,
      "EB01-046": 4,
      "OP07-080": 1,
      "OP08-084": 3,
      "OP08-091": 1,
      "OP02-117": 4,
      "OP03-097": 1,
      "OP07-096": 4
    }
  },
  {
    "deck_name": "Green Purple Luffy",
    "author": "Deks",
    "date": "2/23/2025",
    "country": "PH",
    "tournament": "Flagship(4-0)",
    "placement": "1st Place",
    "host": "Courtside",
    "decklist": {
      "EB02-010": 1,
      "EB02-035": 4,
      "EB02-061": 4,
      "OP07-064": 4,
      "OP07-066": 4,
      "ST18-001": 4,
      "ST18-004": 4,
      "OP09-073": 4,
      "EB02-017": 4,
      "OP01-119": 2,
      "OP03-072": 2,
      "OP05-076": 4,
      "EB02-041": 4,
      "OP09-078": 4,
      "OP07-036": 2
    }
  },
  {
    "deck_name": "Red Shanks",
    "author": "Yukiame",
    "date": "2/23/2025",
    "country": "JP",
    "tournament": "Flagship(5-0)",
    "placement": "1st Place",
    "host": "Game Ark(32)",
    "decklist": {
      "OP09-001": 1,
      "OP01-006": 4,
      "OP06-007": 2,
      "OP08-118": 4,
      "OP09-002": 4,
      "OP09-004": 4,
      "OP09-005": 2,
      "OP09-008": 3,
      "OP09-009": 4,
      "OP09-011": 4,
      "OP09-013": 4,
      "OP09-014": 2,
      "OP09-015": 4,
      "OP10-011": 4,
      "OP04-016": 2,
      "OP10-019": 3
    }
  },
  {
    "deck_name": "Red Shanks",
    "author": "Simsim",
    "date": "2/23/2025",
    "country": "JP",
    "tournament": "Flagship(5-0)",
    "placement": "1st Place",
    "host": "Seiyu Okazaki",
    "decklist": {
      "OP09-001": 1,
      "OP01-006": 2,
      "ST15-002": 3,
      "ST15-005": 4,
      "OP07-015": 4,
      "OP09-002": 4,
      "OP09-004": 4,
      "OP09-005": 2,
      "OP09-009": 4,
      "OP09-011": 4,
      "OP09-013": 3,
      "OP09-014": 4,
      "OP09-015": 4,
      "OP09-118": 2,
      "OP10-011": 4,
      "OP10-019": 2
    }
  },
  {
    "deck_name": "Smoker",
    "author": "FM",
    "date": "2/23/2025",
    "country": "JP",
    "tournament": "FLagship(4-0)",
    "placement": "1st Place",
    "host": "Cardshop",
    "decklist": {
      "OP02-093": 1,
      "OP02-096": 4,
      "OP02-098": 1,
      "ST06-006": 4,
      "ST06-008": 2,
      "OP02-106": 4,
      "OP03-089": 4,
      "OP05-091": 4,
      "OP06-086": 4,
      "EB01-046": 4,
      "EB01-049": 3,
      "EB02-044": 2,
      "OP08-084": 2,
      "ST19-002": 4,
      "ST19-003": 4,
      "OP02-117": 4
    }
  },
  {
    "deck_name": "Purple Luffy",
    "author": "Leo",
    "date": "2/23/2025",
    "country": "JP",
    "tournament": "Flagship(5-0)",
    "placement": "1st Place",
    "host": "Cardshop",
    "decklist": {
      "OP05-060": 1,
      "ST10-008": 3,
      "OP05-070": 4,
      "OP05-074": 4,
      "OP06-076": 4,
      "OP08-069": 2,
      "ST18-001": 4,
      "ST18-002": 4,
      "ST18-003": 4,
      "ST18-004": 4,
      "ST18-005": 4,
      "OP09-119": 2,
      "OP09-065": 3,
      "OP09-069": 4,
      "OP09-078": 4
    }
  },
  {
    "deck_name": "Yellow Enel",
    "author": "Mii",
    "date": "2/22/2025",
    "country": "JP",
    "tournament": "Flagship(5-0)",
    "placement": "1st Place",
    "host": "Amedori",
    "decklist": {
      "OP05-098": 1,
      "OP03-116": 1,
      "OP03-123": 4,
      "OP04-100": 4,
      "OP04-112": 4,
      "OP05-102": 4,
      "OP06-111": 4,
      "EB01-056": 4,
      "EB01-057": 4,
      "EB02-052": 3,
      "EB02-054": 2,
      "OP07-107": 2,
      "OP07-119": 3,
      "OP08-106": 4,
      "OP06-115": 4,
      "EB01-059": 3
    }
  },
  {
    "deck_name": "Teach",
    "author": "Riyu",
    "date": "2/22/2025",
    "country": "JP",
    "tournament": "Shop Event(9-0)",
    "placement": "1st Place",
    "host": "Shake Pirates Cup",
    "decklist": {
      "OP09-081": 1,
      "EB01-048": 2,
      "OP09-083": 4,
      "OP09-086": 4,
      "OP09-088": 2,
      "OP09-089": 4,
      "OP09-090": 4,
      "OP09-091": 2,
      "OP09-093": 4,
      "OP09-095": 4,
      "OP10-082": 4,
      "OP02-117": 4,
      "OP09-096": 4,
      "OP09-098": 2,
      "OP09-099": 4,
      "OP10-098": 2
    }
  },
  {
    "deck_name": "Teach",
    "author": "Hane",
    "date": "2/22/2025",
    "country": "JP",
    "tournament": "3v3(7-1)",
    "placement": "1st Place",
    "host": "Hanamaru Cup",
    "decklist": {
      "OP09-081": 1,
      "EB01-048": 2,
      "OP09-083": 4,
      "OP09-086": 4,
      "OP09-088": 2,
      "OP09-089": 4,
      "OP09-090": 4,
      "OP09-091": 2,
      "OP09-093": 4,
      "OP09-095": 4,
      "OP10-082": 4,
      "OP02-117": 4,
      "OP09-096": 4,
      "OP09-098": 2,
      "OP09-099": 4,
      "OP10-098": 2
    }
  },
  {
    "deck_name": "Red Shanks",
    "author": "Jonathan Emon",
    "date": "2/22/2025",
    "country": "Indonesia",
    "tournament": "SB",
    "placement": "1st Place",
    "host": "Vanguard Clinic",
    "decklist": {
      "OP09-001": 1,
      "OP01-006": 4,
      "ST15-002": 2,
      "OP06-007": 2,
      "OP08-118": 4,
      "OP09-002": 4,
      "OP09-004": 3,
      "OP09-008": 4,
      "OP09-009": 4,
      "OP09-011": 4,
      "OP09-013": 4,
      "OP09-014": 2,
      "OP09-015": 4,
      "OP10-011": 3,
      "OP04-016": 2,
      "OP09-021": 2,
      "OP10-019": 2
    }
  },
  {
    "deck_name": "Green Bonney",
    "author": "Raphterra",
    "date": "2/22/2025",
    "country": "PH",
    "tournament": "3v3(5-0)",
    "placement": "1st Place",
    "host": "GamersShop",
    "decklist": {
      "OP07-019": 1,
      "OP01-039": 3,
      "OP01-051": 4,
      "OP01-054": 1,
      "ST02-007": 4,
      "ST02-008": 3,
      "OP01-052": 1,
      "OP04-031": 2,
      "OP05-030": 4,
      "OP06-035": 3,
      "EB01-012": 4,
      "EB01-015": 4,
      "EB02-015": 1,
      "ST16-004": 3,
      "OP08-023": 4,
      "OP10-030": 3,
      "OP10-032": 4,
      "OP05-037": 2
    }
  },
  {
    "deck_name": "Green Purple Luffy",
    "author": "DeksV81992",
    "date": "2/22/2025",
    "country": "PH",
    "tournament": "3v3",
    "placement": "1st Place",
    "host": "GamersShop",
    "decklist": {
      "EB02-010": 1,
      "EB02-035": 4,
      "EB02-061": 4,
      "OP07-064": 4,
      "OP07-066": 4,
      "ST18-001": 4,
      "ST18-004": 4,
      "OP09-073": 4,
      "EB02-017": 4,
      "OP01-119": 2,
      "OP03-072": 2,
      "OP05-076": 4,
      "EB02-041": 4,
      "OP09-078": 4,
      "OP07-036": 2
    }
  },
  {
    "deck_name": "Teach",
    "author": "reynyelbrefe",
    "date": "2/22/2025",
    "country": "PH",
    "tournament": "3v3",
    "placement": "1st Place",
    "host": "GamersShop",
    "decklist": {
      "OP09-081": 1,
      "OP09-083": 4,
      "OP09-086": 4,
      "OP09-088": 2,
      "OP09-089": 4,
      "OP09-090": 4,
      "OP09-091": 2,
      "OP09-093": 4,
      "OP09-095": 4,
      "OP10-082": 4,
      "OP02-117": 4,
      "OP09-096": 4,
      "OP09-098": 3,
      "OP09-099": 4,
      "OP10-098": 3
    }
  },
  {
    "deck_name": "Teach",
    "author": "Matthew Marginet",
    "date": "2/22/2025",
    "country": "PH",
    "tournament": "FLagship(4-0)",
    "placement": "1st Place",
    "host": "TopDeck Games",
    "decklist": {
      "OP09-081": 1,
      "OP09-083": 4,
      "OP09-086": 4,
      "OP09-088": 2,
      "OP09-089": 4,
      "OP09-090": 4,
      "OP09-091": 2,
      "OP09-093": 4,
      "OP09-095": 4,
      "OP10-082": 4,
      "EB01-051": 4,
      "OP09-096": 4,
      "OP09-098": 3,
      "OP09-099": 4,
      "OP10-098": 3
    }
  },
  {
    "deck_name": "Green Purple Luffy",
    "author": "Kuma",
    "date": "2/22/2025",
    "country": "JP",
    "tournament": "Flagship(5-0)",
    "placement": "1st Place",
    "host": "Cardship",
    "decklist": {
      "EB02-010": 1,
      "OP05-070": 3,
      "EB02-035": 4,
      "EB02-036": 2,
      "EB02-061": 4,
      "OP07-064": 4,
      "ST18-001": 4,
      "ST18-004": 4,
      "OP09-063": 2,
      "EB02-017": 4,
      "EB02-019": 3,
      "OP03-072": 1,
      "OP05-076": 3,
      "EB02-041": 4,
      "OP09-078": 4,
      "OP08-036": 4
    }
  },
  {
    "deck_name": "Purple Luffy",
    "author": "Raisu",
    "date": "2/22/2025",
    "country": "JP",
    "tournament": "FLagship(4-0)",
    "placement": "1st Place",
    "host": "Oretan",
    "decklist": {
      "OP05-060": 1,
      "ST10-010": 2,
      "OP05-070": 2,
      "OP05-074": 4,
      "OP06-076": 4,
      "OP07-064": 4,
      "OP08-069": 2,
      "ST18-001": 4,
      "ST18-002": 2,
      "ST18-003": 4,
      "ST18-004": 4,
      "ST18-005": 4,
      "OP09-119": 2,
      "OP09-065": 3,
      "OP09-069": 4,
      "OP05-077": 1,
      "OP09-078": 4
    }
  },
  {
    "deck_name": "Green Purple Luffy",
    "author": "Ren",
    "date": "2/22/2025",
    "country": "JP",
    "tournament": "3v3(7-0)",
    "placement": "Top-4",
    "host": "Hanamaru Cup",
    "decklist": {
      "EB02-010": 1,
      "OP05-070": 3,
      "EB02-035": 4,
      "EB02-061": 4,
      "OP07-064": 4,
      "OP07-066": 3,
      "ST18-001": 4,
      "ST18-004": 4,
      "ST18-005": 2,
      "EB02-017": 4,
      "EB02-019": 4,
      "OP03-072": 2,
      "EB02-041": 4,
      "OP09-078": 4,
      "OP08-036": 4
    }
  },
  {
    "deck_name": "BY Luffy",
    "author": "Kamui",
    "date": "2/22/2025",
    "country": "JP",
    "tournament": "3v3(8-1)",
    "placement": "3rd Place",
    "host": "Saikyo Cup",
    "decklist": {
      "ST13-003": 1,
      "OP06-106": 4,
      "ST13-007": 4,
      "ST13-008": 1,
      "ST13-013": 4,
      "ST13-014": 4,
      "ST13-015": 4,
      "EB01-056": 4,
      "OP07-109": 4,
      "OP10-103": 3,
      "OP02-096": 4,
      "OP04-083": 4,
      "OP06-086": 4,
      "ST13-019": 3,
      "EB01-059": 3
    }
  },
  {
    "deck_name": "BY Luffy",
    "author": "sypokeca",
    "date": "2/22/2025",
    "country": "JP",
    "tournament": "Shop Event",
    "placement": "1st Place",
    "host": "oneyobi_ch",
    "decklist": {
      "ST13-003": 1,
      "OP06-106": 4,
      "OP06-111": 2,
      "ST13-007": 4,
      "ST13-008": 2,
      "ST13-012": 1,
      "ST13-013": 4,
      "ST13-014": 4,
      "ST13-015": 4,
      "EB01-056": 4,
      "OP07-109": 4,
      "OP02-096": 3,
      "OP04-083": 4,
      "OP06-086": 4,
      "ST13-019": 3,
      "EB01-059": 3
    }
  },
  {
    "deck_name": "Kid",
    "author": "Mototomo",
    "date": "2/22/2025",
    "country": "JP",
    "tournament": "3v3(8-0)",
    "placement": "1st Place",
    "host": "Rou TV Cup",
    "decklist": {
      "OP10-099": 1,
      "OP04-100": 4,
      "P-088": 4,
      "OP05-102": 4,
      "EB01-057": 4,
      "OP07-119": 4,
      "OP08-106": 3,
      "OP10-105": 3,
      "OP10-108": 3,
      "OP10-111": 4,
      "OP10-112": 4,
      "OP10-113": 4,
      "OP10-114": 4,
      "OP10-119": 4,
      "OP10-116": 1
    }
  },
  {
    "deck_name": "Smoker",
    "author": "Shum Jia Yu",
    "date": "2/22/2025",
    "country": "SG",
    "tournament": "FLagship(4-0)",
    "placement": "1st Place",
    "host": "Imaginarium",
    "decklist": {
      "OP02-093": 1,
      "OP02-096": 4,
      "OP02-098": 2,
      "ST06-006": 4,
      "ST06-008": 3,
      "OP02-106": 4,
      "OP03-089": 4,
      "OP05-091": 4,
      "OP06-086": 4,
      "EB01-046": 4,
      "EB01-049": 2,
      "OP07-085": 1,
      "OP08-079": 2,
      "ST19-002": 4,
      "ST19-003": 4,
      "OP02-117": 4
    }
  },
  {
    "deck_name": "Smoker",
    "author": "Reps",
    "date": "2/22/2025",
    "country": "Malaysia",
    "tournament": "SB",
    "placement": "1st Place",
    "host": "Sky Pillar",
    "decklist": {
      "OP02-093": 1,
      "OP02-121": 1,
      "OP02-114": 2,
      "OP02-098": 2,
      "ST06-006": 4,
      "ST06-008": 4,
      "OP02-106": 4,
      "OP03-078": 1,
      "OP03-089": 4,
      "OP05-091": 4,
      "OP06-086": 4,
      "EB01-046": 4,
      "EB01-049": 2,
      "OP08-079": 2,
      "ST19-002": 4,
      "ST19-003": 4,
      "OP02-117": 4
    }
  },
  {
    "deck_name": "Black Lucci",
    "author": "Taku",
    "date": "2/22/2025",
    "country": "JP",
    "tournament": "Flagship(5-0)",
    "placement": "1st Place",
    "host": "Tsutaya",
    "decklist": {
      "OP07-079": 1,
      "OP02-106": 4,
      "OP03-080": 3,
      "OP03-081": 4,
      "OP03-086": 4,
      "OP04-083": 1,
      "OP05-091": 4,
      "OP05-093": 4,
      "OP06-086": 4,
      "EB01-043": 2,
      "EB01-046": 4,
      "OP07-080": 1,
      "OP08-079": 2,
      "OP08-084": 3,
      "OP08-091": 1,
      "OP02-117": 4,
      "OP03-097": 1,
      "OP07-096": 4
    }
  },
  {
    "deck_name": "Blue Nami",
    "author": "youtyan6",
    "date": "2/21/2025",
    "country": "JP",
    "tournament": "Flagship(5-0)",
    "placement": "1st Place",
    "host": "Cardshop",
    "decklist": {
      "OP03-040": 1,
      "OP03-044": 4,
      "OP03-048": 2,
      "OP03-050": 2,
      "OP04-041": 4,
      "OP07-054": 2,
      "OP09-050": 4,
      "ST03-017": 4,
      "OP01-088": 4,
      "OP02-066": 4,
      "OP03-054": 4,
      "OP03-055": 4,
      "OP03-056": 4,
      "OP06-059": 4,
      "OP07-055": 4
    }
  },
  {
    "deck_name": "Red Shanks",
    "author": "Rampen",
    "date": "2/20/2025",
    "country": "JP",
    "tournament": "Flagship(5-0)",
    "placement": "1st Place",
    "host": "Cardshop",
    "decklist": {
      "OP09-001": 1,
      "OP01-006": 4,
      "ST15-002": 2,
      "OP08-118": 4,
      "OP09-002": 4,
      "OP09-004": 4,
      "OP09-008": 3,
      "OP09-009": 4,
      "OP09-011": 4,
      "OP09-013": 4,
      "OP09-014": 4,
      "OP09-015": 3,
      "OP10-011": 4,
      "ST21-014": 2,
      "OP04-016": 2,
      "OP09-020": 1,
      "OP10-019": 1
    }
  },
  {
    "deck_name": "Red Blue Marco",
    "author": "Kanpa",
    "date": "2/20/2025",
    "country": "JP",
    "tournament": "Flagship(5-0)",
    "placement": "1st Place",
    "host": "Bookoff(32)",
    "decklist": {
      "OP08-002": 1,
      "OP01-006": 4,
      "OP02-008": 4,
      "OP02-011": 3,
      "OP02-013": 2,
      "OP03-003": 4,
      "OP03-013": 2,
      "ST15-002": 4,
      "OP08-118": 4,
      "OP10-011": 4,
      "OP08-040": 4,
      "OP08-047": 4,
      "FB02-026": 4,
      "OP01-029": 3,
      "OP10-019": 4
    }
  },
  {
    "deck_name": "Teach",
    "author": "Hane",
    "date": "2/20/2025",
    "country": "JP",
    "tournament": "Flagship(5-0)",
    "placement": "1st Place",
    "host": "Kawasaki",
    "decklist": {
      "OP09-081": 1,
      "EB01-048": 2,
      "OP09-083": 4,
      "OP09-086": 4,
      "OP09-088": 2,
      "OP09-089": 4,
      "OP09-090": 4,
      "OP09-091": 2,
      "OP09-093": 4,
      "OP09-095": 4,
      "OP10-082": 4,
      "OP02-117": 4,
      "OP09-096": 4,
      "OP09-098": 1,
      "OP09-099": 4,
      "OP10-098": 3
    }
  },
  {
    "deck_name": "RG Chopper",
    "author": "onepiece_xy",
    "date": "2/17/2025",
    "country": "JP",
    "tournament": "SB(3-0)",
    "placement": "1st Place",
    "host": "Cardshop",
    "decklist": {
      "OP08-001": 1,
      "OP01-016": 4,
      "OP01-013": 4,
      "OP01-015": 2,
      "OP04-009": 2,
      "EB01-006": 4,
      "OP08-007": 4,
      "OP08-010": 4,
      "OP08-016": 4,
      "OP06-035": 2,
      "EB02-016": 3,
      "EB02-017": 3,
      "OP09-029": 4,
      "ST01-014": 4,
      "EB01-009": 4,
      "ST21-017": 1,
      "EB02-021": 1
    }
  },
  {
    "deck_name": "Green Bonney",
    "author": "Nameko",
    "date": "2/16/2025",
    "country": "JP",
    "tournament": "Shop Event",
    "placement": "1st Place",
    "host": "Waiwai CS(38)",
    "decklist": {
      "OP07-019": 1,
      "OP01-039": 2,
      "ST02-007": 4,
      "ST02-008": 4,
      "OP04-031": 4,
      "OP05-030": 4,
      "OP06-118": 1,
      "OP06-035": 4,
      "EB01-012": 4,
      "EB01-015": 2,
      "ST16-004": 4,
      "OP07-026": 1,
      "OP07-029": 3,
      "OP08-023": 4,
      "OP10-030": 2,
      "OP10-032": 4,
      "OP05-037": 3
    }
  },
  {
    "deck_name": "Kid",
    "author": "Yashaharu",
    "date": "2/16/2025",
    "country": "JP",
    "tournament": "Flagship",
    "placement": "1st Place",
    "host": "Tsutaya",
    "decklist": {
      "OP10-099": 1,
      "P-088": 4,
      "OP05-102": 2,
      "OP05-105": 4,
      "ST13-008": 4,
      "EB01-057": 4,
      "OP07-119": 4,
      "OP09-107": 4,
      "OP10-108": 3,
      "OP10-109": 4,
      "OP10-111": 4,
      "OP10-112": 4,
      "OP10-114": 4,
      "OP10-119": 4,
      "OP05-115": 1
    }
  },
  {
    "deck_name": "Smoker",
    "author": "Reps",
    "date": "2/16/2025",
    "country": "SG",
    "tournament": "Flagship(4-0)",
    "placement": "1st Place",
    "host": "Duellers Point",
    "decklist": {
      "OP02-093": 1,
      "OP02-121": 1,
      "OP02-114": 2,
      "OP02-098": 2,
      "ST06-006": 4,
      "ST06-008": 4,
      "OP02-106": 4,
      "OP03-078": 1,
      "OP03-089": 4,
      "OP05-091": 4,
      "OP06-086": 4,
      "EB01-046": 4,
      "EB01-049": 2,
      "OP08-079": 2,
      "ST19-002": 4,
      "ST19-003": 4,
      "OP02-117": 4
    }
  },
  {
    "deck_name": "Black Lucci",
    "author": "s0menyy",
    "date": "2/16/2025",
    "country": "JP",
    "tournament": "3v3(7-1)",
    "placement": "1st Place",
    "host": "Soda Cup",
    "decklist": {
      "OP07-079": 1,
      "ST06-010": 1,
      "OP02-106": 4,
      "OP03-080": 3,
      "OP03-081": 4,
      "OP03-086": 4,
      "OP04-083": 1,
      "OP05-091": 4,
      "OP05-093": 4,
      "OP06-086": 4,
      "EB01-043": 2,
      "EB01-046": 4,
      "OP07-080": 1,
      "OP08-084": 3,
      "OP08-091": 1,
      "OP02-117": 4,
      "OP03-095": 1,
      "OP03-097": 1,
      "OP07-096": 4
    }
  },
  {
    "deck_name": "Black Lucci",
    "author": "Gia Khang",
    "date": "2/15/2025",
    "country": "Vietnam",
    "tournament": "Shop Event",
    "placement": "1st Place",
    "host": "Alpha Hobby n Arceus TCG(18)",
    "decklist": {
      "OP07-079": 1,
      "ST06-010": 1,
      "OP02-106": 4,
      "OP03-080": 2,
      "OP03-081": 4,
      "OP03-086": 4,
      "OP04-083": 1,
      "OP05-091": 4,
      "OP05-093": 4,
      "OP06-086": 4,
      "OP06-092": 2,
      "EB01-043": 2,
      "EB01-046": 3,
      "OP08-084": 3,
      "OP08-091": 2,
      "OP02-117": 4,
      "OP03-095": 1,
      "OP03-097": 1,
      "OP07-096": 4
    }
  },
  {
    "deck_name": "Green Purple Luffy",
    "author": "Taji",
    "date": "2/15/2025",
    "country": "JP",
    "tournament": "Flagship(5-0)",
    "placement": "1st Place",
    "host": "Chiba Lab",
    "decklist": {
      "EB02-010": 1,
      "OP05-070": 2,
      "EB02-035": 4,
      "EB02-061": 4,
      "OP07-064": 4,
      "OP07-066": 4,
      "ST18-001": 4,
      "ST18-002": 2,
      "ST18-004": 4,
      "EB02-017": 4,
      "EB02-019": 2,
      "OP01-119": 2,
      "OP05-076": 4,
      "EB02-041": 4,
      "OP09-078": 4,
      "OP08-036": 2
    }
  },
  {
    "deck_name": "Smoker",
    "author": "Ippo",
    "date": "2/15/2025",
    "country": "JP",
    "tournament": "Flagship(5-0)",
    "placement": "1st Place",
    "host": "Cardshop",
    "decklist": {
      "OP02-093": 1,
      "OP02-114": 2,
      "OP02-096": 3,
      "OP02-098": 2,
      "ST06-006": 4,
      "ST06-008": 2,
      "OP02-106": 4,
      "OP03-089": 4,
      "OP05-091": 4,
      "OP06-086": 4,
      "EB01-046": 4,
      "EB01-049": 2,
      "OP08-079": 3,
      "ST19-002": 4,
      "ST19-003": 4,
      "OP02-117": 4
    }
  },
  {
    "deck_name": "Lim Odyssey",
    "author": "Chokochan",
    "date": "2/14/2025",
    "country": "JP",
    "tournament": "Shop Event(4-0)",
    "placement": "1st Place",
    "host": "Tsumu Silver Cup",
    "decklist": {
      "OP09-022": 1,
      "OP01-051": 3,
      "OP06-118": 1,
      "OP09-023": 3,
      "OP09-026": 4,
      "OP09-027": 4,
      "OP09-031": 4,
      "OP09-035": 4,
      "OP09-037": 4,
      "OP10-024": 4,
      "OP10-025": 4,
      "OP10-029": 3,
      "OP10-033": 4,
      "OP10-037": 4,
      "ST18-001": 4
    }
  },
  {
    "deck_name": "Red Shanks",
    "author": "Regal",
    "date": "2/14/2025",
    "country": "JP",
    "tournament": "Shop Event",
    "placement": "1st Place",
    "host": "Pistol Cup",
    "decklist": {
      "OP09-001": 1,
      "OP01-006": 4,
      "OP01-013": 2,
      "ST15-002": 2,
      "OP06-007": 2,
      "OP08-118": 4,
      "OP09-004": 3,
      "OP09-008": 3,
      "OP09-009": 4,
      "OP09-011": 4,
      "OP09-013": 4,
      "OP09-014": 2,
      "OP09-015": 4,
      "OP10-011": 4,
      "ST21-014": 4,
      "OP04-016": 2,
      "OP10-019": 2
    }
  },
  {
    "deck_name": "BY Luffy",
    "author": "Suzutaku",
    "date": "2/14/2025",
    "country": "JP",
    "tournament": "Flagship(5-0)",
    "placement": "1st Place",
    "host": "Cardshop",
    "decklist": {
      "ST13-003": 1,
      "P-073": 1,
      "OP06-106": 4,
      "ST13-007": 4,
      "ST13-008": 2,
      "ST13-013": 4,
      "ST13-014": 4,
      "ST13-015": 4,
      "EB01-056": 4,
      "OP07-109": 4,
      "OP10-103": 2,
      "OP02-096": 3,
      "OP04-083": 4,
      "OP06-086": 4,
      "ST13-019": 2,
      "EB01-059": 2,
      "EB02-058": 2
    }
  },
  {
    "deck_name": "Blue Doffy",
    "author": "Motsuni",
    "date": "2/12/2025",
    "country": "JP",
    "tournament": "Flagship(5-0)",
    "placement": "1st Place",
    "host": "Batoloco",
    "decklist": {
      "OP01-060": 1,
      "ST03-005": 3,
      "ST03-004": 1,
      "OP01-070": 1,
      "OP01-077": 4,
      "OP03-044": 1,
      "OP06-047": 2,
      "EB01-023": 4,
      "OP07-040": 4,
      "OP07-045": 4,
      "OP07-046": 4,
      "OP08-047": 3,
      "ST17-002": 4,
      "ST17-003": 3,
      "ST17-004": 4,
      "ST17-005": 4,
      "OP06-058": 3,
      "OP07-057": 1
    }
  },
  {
    "deck_name": "Blue Doffy",
    "author": "Dokuda",
    "date": "2/12/2025",
    "country": "JP",
    "tournament": "Flagship(5-0)",
    "placement": "1st Place",
    "host": "Tsutaya(32)",
    "decklist": {
      "OP01-060": 1,
      "ST03-005": 4,
      "OP01-077": 4,
      "OP02-054": 3,
      "OP06-047": 3,
      "EB01-023": 4,
      "OP07-040": 4,
      "OP07-045": 4,
      "OP07-046": 4,
      "ST17-002": 4,
      "ST17-003": 4,
      "ST17-004": 4,
      "ST17-005": 4,
      "OP06-058": 4
    }
  },
  {
    "deck_name": "Green Purple Luffy",
    "author": "Sakanoko",
    "date": "2/12/2025",
    "country": "JP",
    "tournament": "Flagship(5-0)",
    "placement": "1st Place",
    "host": "Kohoku Book",
    "decklist": {
      "EB02-010": 1,
      "EB02-035": 4,
      "EB02-061": 4,
      "OP07-064": 4,
      "OP07-066": 4,
      "ST18-001": 4,
      "ST18-004": 4,
      "EB02-017": 4,
      "EB02-019": 4,
      "OP01-119": 2,
      "OP03-072": 2,
      "OP05-076": 4,
      "EB02-041": 4,
      "OP09-078": 4,
      "OP08-036": 2
    }
  },
  {
    "deck_name": "Crocodile",
    "author": "Sanosuke",
    "date": "2/11/2025",
    "country": "JP",
    "tournament": "off-meta",
    "placement": "1st Place",
    "host": "Cardshop",
    "decklist": {
      "ST03-001": 1,
      "ST03-005": 4,
      "ST03-008": 4,
      "ST03-009": 2,
      "OP01-073": 4,
      "ST12-014": 2,
      "EB01-023": 4,
      "OP07-040": 4,
      "OP07-045": 4,
      "OP07-046": 4,
      "OP08-047": 4,
      "ST17-002": 4,
      "ST17-003": 4,
      "OP10-046": 2,
      "OP04-056": 2,
      "OP06-058": 2
    }
  },
  {
    "deck_name": "Green Bonney",
    "author": "Chacha",
    "date": "2/11/2025",
    "country": "JP",
    "tournament": "Flagship(4-0)",
    "placement": "1st Place",
    "host": "Cardshop",
    "decklist": {
      "OP07-019": 1,
      "ST02-004": 4,
      "OP01-051": 4,
      "ST02-007": 4,
      "ST02-008": 4,
      "OP05-030": 4,
      "OP06-118": 4,
      "OP06-035": 4,
      "EB01-012": 4,
      "EB01-015": 4,
      "OP08-023": 4,
      "OP10-030": 2,
      "OP10-032": 4,
      "OP05-037": 4
    }
  },
  {
    "deck_name": "Red Purple Luffy",
    "author": "salmon_onepiece",
    "date": "2/11/2025",
    "country": "JP",
    "tournament": "Flagship(5-0)",
    "placement": "1st Place",
    "host": "Tsuchiura",
    "decklist": {
      "ST10-002": 1,
      "OP05-067": 4,
      "OP05-073": 4,
      "EB01-061": 4,
      "EB02-036": 4,
      "EB02-061": 3,
      "OP07-064": 4,
      "ST18-001": 3,
      "ST18-002": 4,
      "OP09-119": 4,
      "OP01-016": 4,
      "OP02-004": 4,
      "OP10-011": 1,
      "OP09-078": 4,
      "OP10-019": 3
    }
  },
  {
    "deck_name": "Black Lucci",
    "author": "Buku",
    "date": "2/11/2025",
    "country": "JP",
    "tournament": "3v3(7-0)",
    "placement": "1st Place",
    "host": "Sonoda Cup",
    "decklist": {
      "OP07-079": 1,
      "OP02-106": 4,
      "OP03-080": 3,
      "OP03-081": 4,
      "OP03-086": 4,
      "OP05-091": 4,
      "OP05-093": 4,
      "OP06-086": 4,
      "EB01-043": 2,
      "EB01-046": 4,
      "OP07-080": 1,
      "OP08-079": 2,
      "OP08-084": 3,
      "OP08-091": 1,
      "OP02-117": 4,
      "OP03-097": 2,
      "OP07-096": 4
    }
  },
  {
    "deck_name": "Black Lucci",
    "author": "Towa",
    "date": "2/11/2025",
    "country": "JP",
    "tournament": "Flagship(5-0)",
    "placement": "1st Place",
    "host": "Shimakita",
    "decklist": {
      "OP07-079": 1,
      "ST06-008": 2,
      "OP02-106": 4,
      "OP03-080": 3,
      "OP03-081": 4,
      "OP03-086": 3,
      "OP04-083": 1,
      "OP05-091": 4,
      "OP05-093": 4,
      "OP06-086": 4,
      "EB01-043": 2,
      "EB01-046": 4,
      "OP07-080": 1,
      "OP08-084": 3,
      "OP08-091": 1,
      "OP02-117": 4,
      "OP03-095": 1,
      "OP03-097": 1,
      "OP07-096": 4
    }
  },
  {
    "deck_name": "Red Green Smoker",
    "author": "Matsuno",
    "date": "2/9/2025",
    "country": "JP",
    "tournament": "Japan Final",
    "placement": "1st Place",
    "host": "Bandai(63)",
    "decklist": {
      "OP10-001": 1,
      "OP01-006": 4,
      "OP07-010": 2,
      "OP09-009": 4,
      "OP10-004": 4,
      "OP10-005": 4,
      "OP10-011": 4,
      "OP10-016": 2,
      "OP01-051": 4,
      "OP05-030": 4,
      "OP06-035": 4,
      "OP10-030": 4,
      "OP10-032": 4,
      "OP01-029": 1,
      "OP10-018": 2,
      "ST21-017": 3
    }
  },
  {
    "deck_name": "Green Purple Luffy",
    "author": "Yashamaru",
    "date": "2/9/2025",
    "country": "JP",
    "tournament": "Japan Final(6-2)",
    "placement": "2nd Place",
    "host": "Bandai(63)",
    "decklist": {
      "EB02-010": 1,
      "EB02-035": 4,
      "EB02-036": 2,
      "EB02-061": 4,
      "OP07-064": 4,
      "OP07-066": 4,
      "ST18-001": 4,
      "ST18-004": 4,
      "OP09-073": 4,
      "EB02-017": 4,
      "OP01-119": 4,
      "OP05-076": 4,
      "EB02-041": 4,
      "OP09-078": 4
    }
  },
  {
    "deck_name": "Teach",
    "author": "Fakenoko",
    "date": "2/9/2025",
    "country": "JP",
    "tournament": "Japan Final(4-3)",
    "placement": "Top-8",
    "host": "Bandai(63)",
    "decklist": {
      "OP09-081": 1,
      "OP09-083": 4,
      "OP09-086": 4,
      "OP09-088": 3,
      "OP09-089": 4,
      "OP09-090": 4,
      "OP09-091": 2,
      "OP09-093": 3,
      "OP09-095": 4,
      "OP10-082": 4,
      "EB01-051": 4,
      "OP09-096": 4,
      "OP09-098": 3,
      "OP09-099": 4,
      "OP10-098": 3
    }
  },
  {
    "deck_name": "Green Purple Luffy",
    "author": "Gori",
    "date": "2/8/2025",
    "country": "JP",
    "tournament": "Flagship(5-0)",
    "placement": "1st Place",
    "host": "Bunkyo",
    "decklist": {
      "EB02-010": 1,
      "OP05-067": 2,
      "EB02-035": 4,
      "EB02-036": 3,
      "EB02-037": 4,
      "EB02-061": 3,
      "OP07-064": 4,
      "ST18-001": 4,
      "ST18-004": 4,
      "OP02-041": 1,
      "EB01-014": 2,
      "EB02-017": 4,
      "EB02-019": 3,
      "OP09-033": 2,
      "OP03-072": 1,
      "EB02-041": 4,
      "OP09-078": 4,
      "OP07-036": 1
    }
  },
  {
    "deck_name": "Green Purple Luffy",
    "author": "Sakanoko",
    "date": "2/8/2025",
    "country": "JP",
    "tournament": "Flagship(5-0)",
    "placement": "1st Place",
    "host": "Mizonokuchi",
    "decklist": {
      "EB02-010": 1,
      "OP05-067": 2,
      "EB02-035": 4,
      "EB02-061": 4,
      "OP07-064": 4,
      "OP07-066": 4,
      "ST18-001": 4,
      "ST18-004": 4,
      "EB01-014": 2,
      "EB02-017": 4,
      "EB02-019": 2,
      "OP03-072": 2,
      "OP05-076": 4,
      "OP05-077": 2,
      "EB02-041": 4,
      "OP09-078": 4
    }
  },
  {
    "deck_name": "Green Purple Luffy",
    "author": "Kalish",
    "date": "2/8/2025",
    "country": "Malaysia",
    "tournament": "TB",
    "placement": "1st Place",
    "host": "Fandombase Ventures",
    "decklist": {
      "EB02-010": 1,
      "OP05-067": 2,
      "OP05-070": 4,
      "EB02-035": 4,
      "EB02-036": 2,
      "EB02-061": 4,
      "OP07-064": 4,
      "ST18-001": 4,
      "ST18-004": 4,
      "EB02-017": 4,
      "EB02-019": 2,
      "OP05-076": 4,
      "OP05-077": 1,
      "EB02-041": 4,
      "OP09-078": 4,
      "OP08-036": 3
    }
  },
  {
    "deck_name": "Sugar",
    "author": "Adrie",
    "date": "2/8/2025",
    "country": "PH",
    "tournament": "Flagship(4-0)",
    "placement": "1st Place",
    "host": "LGS",
    "decklist": {
      "OP10-003": 1,
      "EB01-061": 4,
      "EB02-061": 2,
      "OP10-062": 3,
      "OP10-065": 4,
      "OP10-066": 4,
      "OP10-067": 3,
      "OP10-071": 3,
      "OP10-072": 4,
      "OP10-076": 4,
      "OP07-015": 2,
      "OP09-004": 3,
      "OP02-089": 3,
      "OP07-076": 1,
      "OP10-078": 3,
      "OP10-079": 2,
      "OP01-026": 3,
      "OP10-018": 2
    }
  },
  {
    "deck_name": "Purple Luffy",
    "author": "Shuto",
    "date": "2/8/2025",
    "country": "JP",
    "tournament": "Shop Event(7-1)",
    "placement": "1st Place",
    "host": "Cardshop",
    "decklist": {
      "OP05-060": 1,
      "ST10-008": 3,
      "OP05-074": 4,
      "OP06-076": 4,
      "OP07-064": 4,
      "OP08-069": 2,
      "ST18-001": 4,
      "ST18-002": 3,
      "ST18-003": 4,
      "ST18-004": 4,
      "ST18-005": 4,
      "OP09-119": 2,
      "OP09-065": 3,
      "OP09-069": 4,
      "OP05-077": 1,
      "OP09-078": 4
    }
  },
  {
    "deck_name": "Yellow Enel",
    "author": "ammulet77",
    "date": "2/8/2025",
    "country": "JP",
    "tournament": "Flagship(5-0)",
    "placement": "1st Place",
    "host": "Cardshop",
    "decklist": {
      "OP05-098": 1,
      "OP03-123": 4,
      "OP04-100": 4,
      "OP04-112": 4,
      "OP05-102": 4,
      "EB01-056": 4,
      "EB01-057": 4,
      "EB02-052": 3,
      "EB02-054": 4,
      "OP07-107": 4,
      "OP07-119": 4,
      "OP08-106": 4,
      "OP06-115": 4,
      "EB01-059": 3
    }
  },
  {
    "deck_name": "Green Purple Luffy",
    "author": "Deks",
    "date": "2/7/2025",
    "country": "PH",
    "tournament": "Flagship(4-0)",
    "placement": "1st Place",
    "host": "Hobby Stadium(13)",
    "decklist": {
      "EB02-010": 1,
      "OP05-067": 4,
      "EB02-035": 4,
      "EB02-037": 4,
      "EB02-061": 4,
      "OP07-064": 4,
      "ST18-001": 4,
      "ST18-004": 4,
      "ST18-005": 2,
      "EB01-014": 4,
      "EB02-017": 4,
      "OP03-072": 2,
      "OP05-076": 2,
      "EB02-041": 4,
      "OP09-078": 4
    }
  },
  {
    "deck_name": "Blue Doffy",
    "author": "Winda",
    "date": "2/7/2025",
    "country": "JP",
    "tournament": "Shop Event",
    "placement": "1st Place",
    "host": "Shumai Cup",
    "decklist": {
      "OP01-060": 1,
      "ST03-005": 4,
      "ST03-004": 4,
      "OP01-077": 4,
      "OP03-044": 1,
      "EB01-023": 4,
      "OP07-040": 4,
      "OP07-045": 4,
      "OP07-046": 4,
      "OP08-047": 2,
      "ST17-002": 4,
      "ST17-003": 4,
      "ST17-004": 4,
      "ST17-005": 4,
      "ST03-015": 1,
      "OP07-057": 2
    }
  },
  {
    "deck_name": "Oden",
    "author": "Yuno",
    "date": "2/7/2025",
    "country": "JP",
    "tournament": "Flagship(5-0)",
    "placement": "1st Place",
    "host": "Corgi(32)",
    "decklist": {
      "EB01-001": 1,
      "OP03-003": 4,
      "EB01-007": 2,
      "EB02-006": 4,
      "OP09-118": 2,
      "ST21-014": 4,
      "OP01-033": 4,
      "OP01-041": 4,
      "OP01-046": 4,
      "OP02-042": 2,
      "OP05-030": 4,
      "OP06-035": 3,
      "EB01-013": 4,
      "OP07-022": 4,
      "OP01-029": 3,
      "OP01-055": 2
    }
  },
  {
    "deck_name": "Vegapunk",
    "author": "madambeard",
    "date": "2/7/2025",
    "country": "JP",
    "tournament": "SB(4-0)",
    "placement": "1st Place",
    "host": "Fullcomp",
    "decklist": {
      "OP07-097": 1,
      "ST13-011": 4,
      "EB01-056": 3,
      "OP07-100": 4,
      "OP07-101": 4,
      "OP07-105": 4,
      "OP07-107": 4,
      "OP07-109": 4,
      "OP07-110": 2,
      "OP07-111": 4,
      "OP07-098": 4,
      "OP08-106": 4,
      "OP08-112": 1,
      "EB01-059": 2,
      "OP07-115": 4,
      "OP07-117": 2
    }
  },
  {
    "deck_name": "Green Purple Luffy",
    "author": "Piro",
    "date": "2/6/2025",
    "country": "JP",
    "tournament": "Flagship(5-0)",
    "placement": "1st Place",
    "host": "Yagi",
    "decklist": {
      "EB02-010": 1,
      "EB02-035": 4,
      "EB02-036": 3,
      "EB02-061": 3,
      "OP07-064": 4,
      "ST18-001": 4,
      "ST18-004": 2,
      "OP09-070": 2,
      "OP01-051": 2,
      "EB01-014": 2,
      "EB02-017": 4,
      "EB02-019": 4,
      "OP09-033": 2,
      "OP03-072": 1,
      "OP05-076": 3,
      "OP05-077": 2,
      "EB02-041": 4,
      "OP09-078": 4
    }
  },
  {
    "deck_name": "Blue Doffy",
    "author": "Chill",
    "date": "2/5/2025",
    "country": "JP",
    "tournament": "Flagship(5-0)",
    "placement": "1st Place",
    "host": "Cardshop",
    "decklist": {
      "OP01-060": 1,
      "ST03-004": 2,
      "OP01-077": 4,
      "OP03-044": 1,
      "OP06-047": 2,
      "EB01-023": 4,
      "OP07-040": 4,
      "OP07-045": 4,
      "OP07-046": 4,
      "OP07-047": 2,
      "OP08-047": 3,
      "ST17-002": 4,
      "ST17-003": 4,
      "ST17-004": 4,
      "ST17-005": 4,
      "OP04-056": 1,
      "OP06-058": 1,
      "OP07-057": 2
    }
  },
  {
    "deck_name": "Yellow Enel",
    "author": "Kyohe",
    "date": "2/5/2025",
    "country": "JP",
    "tournament": "Shop Event(8-1)",
    "placement": "1st Place",
    "host": "Soda Cup",
    "decklist": {
      "OP05-098": 1,
      "OP03-123": 4,
      "OP04-100": 4,
      "OP04-112": 4,
      "OP06-111": 4,
      "EB01-056": 4,
      "EB01-057": 4,
      "EB02-052": 4,
      "EB02-054": 3,
      "OP07-107": 3,
      "OP07-119": 3,
      "OP08-106": 4,
      "OP06-115": 3,
      "EB01-059": 4,
      "EB02-059": 2
    }
  },
  {
    "deck_name": "Black Lucci",
    "author": "banao111",
    "date": "2/5/2025",
    "country": "JP",
    "tournament": "Flagship(5-0)",
    "placement": "1st Place",
    "host": "PAO",
    "decklist": {
      "OP07-079": 1,
      "ST06-010": 1,
      "OP02-106": 4,
      "OP03-080": 2,
      "OP03-081": 4,
      "OP03-086": 4,
      "OP04-083": 1,
      "OP05-091": 4,
      "OP05-093": 4,
      "OP06-086": 4,
      "EB01-043": 2,
      "EB01-046": 4,
      "OP07-080": 1,
      "OP07-085": 1,
      "OP08-084": 3,
      "OP08-091": 1,
      "OP02-117": 4,
      "OP03-095": 1,
      "OP03-097": 1,
      "OP07-096": 4
    }
  },
  {
    "deck_name": "Red Shanks",
    "author": "Komugi",
    "date": "2/4/2025",
    "country": "JP",
    "tournament": "Flagship(5-0)",
    "placement": "1st Place",
    "host": "Cardshop",
    "decklist": {
      "OP09-001": 1,
      "OP01-006": 4,
      "ST15-002": 3,
      "OP06-007": 3,
      "OP08-118": 4,
      "OP09-002": 4,
      "OP09-004": 3,
      "OP09-005": 3,
      "OP09-008": 3,
      "OP09-009": 4,
      "OP09-011": 4,
      "OP09-013": 4,
      "OP09-014": 2,
      "OP09-015": 3,
      "OP10-011": 4,
      "OP04-016": 2
    }
  },
  {
    "deck_name": "Yellow Green Law",
    "author": "Ini",
    "date": "2/4/2025",
    "country": "JP",
    "tournament": "Flagship(5-0)",
    "placement": "1st Place",
    "host": "Dragon Star",
    "decklist": {
      "OP10-022": 1,
      "P-088": 2,
      "OP10-101": 4,
      "OP10-103": 4,
      "OP10-107": 4,
      "OP10-109": 4,
      "OP10-111": 4,
      "OP10-113": 2,
      "OP10-114": 2,
      "OP10-119": 4,
      "OP01-047": 4,
      "OP01-051": 2,
      "ST02-007": 4,
      "EB01-012": 4,
      "OP07-026": 3,
      "OP10-032": 3
    }
  },
  {
    "deck_name": "Green Purple Luffy",
    "author": "Sakanoko",
    "date": "2/2/2025",
    "country": "JP",
    "tournament": "2v2(5-0)",
    "placement": "1st Place",
    "host": "One Happy",
    "decklist": {
      "EB02-010": 1,
      "OP05-067": 4,
      "EB02-035": 4,
      "EB02-037": 2,
      "EB02-061": 4,
      "OP07-064": 4,
      "OP07-066": 4,
      "ST18-001": 4,
      "ST18-004": 4,
      "EB01-014": 2,
      "EB02-017": 4,
      "OP03-072": 2,
      "OP05-076": 4,
      "EB02-041": 4,
      "OP09-078": 4
    }
  },
  {
    "deck_name": "Red Green Smoker",
    "author": "Ei",
    "date": "2/2/2025",
    "country": "JP",
    "tournament": "Flagship(5-0)",
    "placement": "1st Place",
    "host": "Cardshop",
    "decklist": {
      "OP10-001": 1,
      "OP10-004": 4,
      "OP10-005": 4,
      "OP10-011": 4,
      "OP10-016": 2,
      "OP01-051": 4,
      "OP04-031": 1,
      "OP04-032": 2,
      "OP05-030": 4,
      "OP05-034": 4,
      "OP06-035": 4,
      "OP08-023": 2,
      "OP10-030": 4,
      "OP10-032": 4,
      "OP01-026": 2,
      "OP10-018": 2,
      "ST21-017": 2,
      "OP05-037": 1
    }
  },
  {
    "deck_name": "Red Shanks",
    "author": "Naiki",
    "date": "2/2/2025",
    "country": "JP",
    "tournament": "Flagship(5-0)",
    "placement": "1st Place",
    "host": "Nagashima",
    "decklist": {
      "OP09-001": 1,
      "OP01-006": 4,
      "ST15-002": 3,
      "ST15-005": 4,
      "OP06-007": 3,
      "OP08-118": 3,
      "OP09-002": 4,
      "OP09-004": 3,
      "OP09-008": 3,
      "OP09-009": 3,
      "OP09-011": 4,
      "OP09-013": 4,
      "OP09-014": 3,
      "OP09-015": 3,
      "OP10-011": 4,
      "OP04-016": 2
    }
  },
  {
    "deck_name": "Smoker",
    "author": "D",
    "date": "2/2/2025",
    "country": "JP",
    "tournament": "Flagship(5-0)",
    "placement": "1st Place",
    "host": "Cardshop",
    "decklist": {
      "OP02-093": 1,
      "OP02-114": 2,
      "OP02-096": 3,
      "OP02-098": 2,
      "ST06-006": 4,
      "ST06-008": 2,
      "OP02-106": 4,
      "OP03-089": 4,
      "OP05-091": 4,
      "OP06-086": 4,
      "EB01-046": 4,
      "EB01-049": 2,
      "OP08-084": 3,
      "ST19-002": 4,
      "ST19-003": 4,
      "OP02-117": 4
    }
  },
  {
    "deck_name": "Teach",
    "author": "Deks",
    "date": "2/2/2025",
    "country": "PH",
    "tournament": "Flagship(4-0)",
    "placement": "1st Place",
    "host": "Regran Toys Collectibles(16)",
    "decklist": {
      "OP09-081": 1,
      "OP09-083": 4,
      "OP09-086": 4,
      "OP09-088": 2,
      "OP09-089": 4,
      "OP09-090": 4,
      "OP09-091": 2,
      "OP09-093": 4,
      "OP09-095": 4,
      "OP10-082": 4,
      "OP10-086": 2,
      "EB01-051": 4,
      "OP09-096": 3,
      "OP09-098": 3,
      "OP09-099": 4,
      "OP10-098": 2
    }
  },
  {
    "deck_name": "Teach",
    "author": "USA",
    "date": "2/2/2025",
    "country": "JP",
    "tournament": "Flagship(5-0)",
    "placement": "1st Place",
    "host": "Cardshop",
    "decklist": {
      "OP09-081": 1,
      "EB01-048": 2,
      "OP09-083": 3,
      "OP09-086": 4,
      "OP09-088": 3,
      "OP09-089": 4,
      "OP09-090": 4,
      "OP09-091": 2,
      "OP09-093": 4,
      "OP09-095": 4,
      "OP10-082": 4,
      "EB01-051": 4,
      "OP09-096": 4,
      "OP09-098": 2,
      "OP09-099": 4,
      "OP10-098": 2
    }
  },
  {
    "deck_name": "Red Shanks",
    "author": "Yabu",
    "date": "2/1/2025",
    "country": "JP",
    "tournament": "5v5(8-0)",
    "placement": "1st Place",
    "host": "Trekking Cup",
    "decklist": {
      "OP09-001": 1,
      "OP01-006": 4,
      "OP01-013": 4,
      "ST15-002": 2,
      "OP08-118": 4,
      "OP09-002": 4,
      "OP09-004": 3,
      "OP09-008": 3,
      "OP09-009": 4,
      "OP09-011": 4,
      "OP09-013": 4,
      "OP09-014": 2,
      "OP09-015": 4,
      "ST21-014": 3,
      "OP04-016": 3,
      "OP09-020": 2
    }
  },
  {
    "deck_name": "Green Purple Luffy",
    "author": "Hiiro",
    "date": "2/1/2025",
    "country": "JP",
    "tournament": "Flagship(5-0)",
    "placement": "1st Place",
    "host": "Cardshop",
    "decklist": {
      "EB02-010": 1,
      "OP05-070": 4,
      "EB02-035": 4,
      "EB02-037": 4,
      "EB02-061": 2,
      "OP07-064": 4,
      "OP07-066": 4,
      "ST18-001": 4,
      "ST18-002": 2,
      "ST18-004": 4,
      "ST18-005": 4,
      "EB02-017": 4,
      "EB02-019": 2,
      "OP05-076": 1,
      "EB02-041": 2,
      "OP09-078": 4,
      "OP07-036": 1
    }
  },
  {
    "deck_name": "Green Purple Luffy",
    "author": "Ayakana",
    "date": "2/1/2025",
    "country": "JP",
    "tournament": "Shop Event(9-0)",
    "placement": "1st Place",
    "host": "Unipen Cup",
    "decklist": {
      "EB02-010": 1,
      "OP05-067": 4,
      "EB02-035": 4,
      "EB02-036": 2,
      "EB02-037": 2,
      "EB02-061": 4,
      "OP07-064": 4,
      "ST18-001": 4,
      "ST18-004": 4,
      "EB01-014": 4,
      "EB02-017": 4,
      "EB02-019": 2,
      "OP03-072": 2,
      "OP05-076": 2,
      "EB02-041": 4,
      "OP09-078": 4
    }
  },
  {
    "deck_name": "Black Lucci",
    "author": "Buku",
    "date": "2/1/2025",
    "country": "JP",
    "tournament": "3v3(7-1)",
    "placement": "1st Place",
    "host": "Trekking Cup",
    "decklist": {
      "OP07-079": 1,
      "OP02-106": 4,
      "OP03-080": 3,
      "OP03-081": 4,
      "OP03-086": 4,
      "OP05-091": 4,
      "OP05-093": 4,
      "OP06-086": 4,
      "EB01-043": 2,
      "EB01-046": 4,
      "OP07-080": 1,
      "OP08-079": 2,
      "OP08-084": 3,
      "OP08-091": 1,
      "OP02-117": 4,
      "OP03-097": 2,
      "OP07-096": 4
    }
  },
  {
    "deck_name": "Green Purple Luffy",
    "author": "Hosono",
    "date": "1/31/2025",
    "country": "JP",
    "tournament": "SB",
    "placement": "1st Place",
    "host": "Binks Binks Cup",
    "decklist": {
      "EB02-010": 1,
      "OP05-067": 4,
      "EB02-035": 4,
      "EB02-037": 4,
      "EB02-061": 4,
      "OP07-064": 4,
      "ST18-001": 4,
      "ST18-004": 4,
      "EB01-014": 4,
      "EB02-017": 4,
      "EB02-019": 2,
      "OP03-072": 1,
      "OP05-076": 3,
      "EB02-041": 4,
      "OP09-078": 4
    }
  },
  {
    "deck_name": "Green Purple Luffy",
    "author": "Esu",
    "date": "1/31/2025",
    "country": "JP",
    "tournament": "Shop Event",
    "placement": "1st Place",
    "host": "Shumai Cup",
    "decklist": {
      "EB02-010": 1,
      "EB02-035": 4,
      "EB02-061": 4,
      "OP07-064": 4,
      "ST18-001": 4,
      "ST18-002": 3,
      "ST18-004": 4,
      "OP01-051": 2,
      "EB01-014": 4,
      "EB02-017": 4,
      "EB02-019": 4,
      "OP03-072": 1,
      "OP05-076": 4,
      "EB02-041": 4,
      "OP09-078": 4
    }
  },
  {
    "deck_name": "Green Bonney",
    "author": "Jc",
    "date": "1/31/2025",
    "country": "PH",
    "tournament": "Flagship(5-0)",
    "placement": "1st Place",
    "host": "Japstore",
    "decklist": {
      "OP07-019": 1,
      "OP01-033": 2,
      "OP01-051": 1,
      "ST02-007": 4,
      "OP04-119": 2,
      "OP04-031": 3,
      "OP05-030": 2,
      "OP06-035": 3,
      "EB01-012": 4,
      "EB01-015": 4,
      "EB02-015": 1,
      "ST16-004": 3,
      "ST16-005": 2,
      "OP07-026": 2,
      "OP07-029": 2,
      "OP08-023": 4,
      "OP10-030": 3,
      "OP10-032": 4,
      "OP01-057": 2,
      "OP05-037": 2
    }
  },
  {
    "deck_name": "Red Shanks",
    "author": "Yuta",
    "date": "1/31/2025",
    "country": "JP",
    "tournament": "Flagship(5-0)",
    "placement": "1st Place",
    "host": "Sun Lounge Card Trading",
    "decklist": {
      "OP09-001": 1,
      "OP01-006": 4,
      "OP01-016": 4,
      "ST01-012": 4,
      "OP01-013": 4,
      "OP02-015": 4,
      "OP07-015": 4,
      "OP09-005": 4,
      "OP09-118": 1,
      "OP10-005": 4,
      "OP10-011": 4,
      "ST21-014": 4,
      "OP01-026": 4,
      "ST01-014": 3,
      "OP04-016": 2
    }
  },
  {
    "deck_name": "Black Blue Usopp",
    "author": "uminogi",
    "date": "1/31/2025",
    "country": "JP",
    "tournament": "Flagship(5-0)",
    "placement": "1st Place",
    "host": "Dragon Star",
    "decklist": {
      "OP10-042": 1,
      "OP04-077": 4,
      "OP04-080": 1,
      "OP04-089": 4,
      "OP04-090": 1,
      "OP04-092": 3,
      "OP05-081": 4,
      "OP10-090": 1,
      "OP10-095": 4,
      "OP10-045": 4,
      "OP10-046": 4,
      "OP10-049": 3,
      "OP10-057": 4,
      "OP10-058": 4,
      "OP02-117": 2,
      "OP04-093": 1,
      "OP04-096": 4,
      "OP04-056": 2
    }
  },
  {
    "deck_name": "Green Purple Luffy",
    "author": "Jitsu",
    "date": "1/27/2025",
    "country": "JP",
    "tournament": "SB",
    "placement": "1st Place",
    "host": "Cardshophanjou",
    "decklist": {
      "EB02-010": 1,
      "OP05-067": 4,
      "EB02-035": 4,
      "EB02-036": 4,
      "EB02-037": 2,
      "EB02-061": 4,
      "OP07-064": 4,
      "ST18-001": 4,
      "ST18-004": 4,
      "ST18-005": 4,
      "OP02-041": 2,
      "EB01-014": 2,
      "EB02-017": 4,
      "OP03-072": 2,
      "EB02-021": 2,
      "EB02-041": 4
    }
  },
  {
    "deck_name": "Red Green Oden",
    "author": "Hapigori",
    "date": "1/26/2025",
    "country": "JP",
    "tournament": "SB",
    "placement": "1st Place",
    "host": "toreca_binks",
    "decklist": {
      "EB01-001": 1,
      "OP01-039": 2,
      "OP01-033": 3,
      "OP01-041": 4,
      "OP01-046": 3,
      "OP01-121": 2,
      "OP05-030": 4,
      "OP06-035": 4,
      "OP06-036": 4,
      "EB01-013": 4,
      "OP07-022": 4,
      "OP10-032": 4,
      "EB01-002": 4,
      "EB02-006": 4,
      "OP01-029": 4
    }
  },
  {
    "deck_name": "Green Bonney",
    "author": "Kudo(RAIN)",
    "date": "1/26/2025",
    "country": "JP",
    "tournament": "3v3(7-1)",
    "placement": "NA",
    "host": "Tsutaya",
    "decklist": {
      "OP07-019": 1,
      "OP01-039": 4,
      "OP01-051": 3,
      "ST02-007": 4,
      "ST02-008": 2,
      "OP04-031": 2,
      "OP05-030": 4,
      "OP06-118": 2,
      "OP06-035": 3,
      "EB01-012": 4,
      "EB01-015": 4,
      "ST16-004": 3,
      "OP07-029": 2,
      "OP08-023": 4,
      "OP10-030": 2,
      "OP10-032": 4,
      "OP05-037": 3
    }
  },
  {
    "deck_name": "Yellow Enel",
    "author": "Yudora",
    "date": "1/26/2025",
    "country": "JP",
    "tournament": "3v3(5-1)",
    "placement": "Top-4",
    "host": "Laugh Tale Cup",
    "decklist": {
      "OP05-098": 1,
      "OP03-116": 2,
      "OP03-123": 4,
      "OP04-100": 4,
      "OP04-112": 4,
      "OP05-102": 4,
      "EB01-056": 4,
      "EB01-057": 4,
      "EB02-052": 4,
      "OP07-107": 4,
      "OP07-119": 2,
      "OP08-105": 4,
      "OP08-106": 4,
      "OP06-115": 2,
      "EB01-059": 4
    }
  },
  {
    "deck_name": "Black Blue Usopp",
    "author": "Yamashi",
    "date": "1/26/2025",
    "country": "JP",
    "tournament": "3v3(6-1)",
    "placement": "1st Place",
    "host": "Corgi",
    "decklist": {
      "OP10-042": 1,
      "OP04-077": 4,
      "OP04-083": 2,
      "OP04-089": 4,
      "OP05-081": 4,
      "OP10-090": 4,
      "OP10-095": 4,
      "OP10-045": 4,
      "OP10-046": 4,
      "OP10-049": 4,
      "OP10-057": 4,
      "OP10-058": 4,
      "OP04-093": 2,
      "OP04-096": 4,
      "OP04-056": 2
    }
  },
  {
    "deck_name": "Teach",
    "author": "njiof_",
    "date": "1/26/2025",
    "country": "JP",
    "tournament": "Shop Event(9-1)",
    "placement": "1st Place",
    "host": "Shumai Cup",
    "decklist": {
      "OP09-081": 1,
      "EB01-048": 1,
      "OP09-083": 4,
      "OP09-086": 4,
      "OP09-088": 2,
      "OP09-089": 4,
      "OP09-090": 4,
      "OP09-091": 2,
      "OP09-093": 4,
      "OP09-095": 4,
      "OP10-082": 4,
      "EB01-051": 4,
      "OP09-096": 4,
      "OP09-098": 3,
      "OP09-099": 4,
      "OP10-098": 2
    }
  },
  {
    "deck_name": "Teach",
    "author": "Hane",
    "date": "1/26/2025",
    "country": "JP",
    "tournament": "3v3(6-1)",
    "placement": "1st Place",
    "host": "Corgi",
    "decklist": {
      "OP09-081": 1,
      "EB01-048": 1,
      "OP09-083": 4,
      "OP09-086": 4,
      "OP09-088": 2,
      "OP09-089": 4,
      "OP09-090": 4,
      "OP09-091": 2,
      "OP09-093": 4,
      "OP09-095": 4,
      "OP10-082": 4,
      "EB01-051": 4,
      "OP09-096": 4,
      "OP09-098": 3,
      "OP09-099": 4,
      "OP10-098": 2
    }
  },
  {
    "deck_name": "Smoker",
    "author": "Hosso",
    "date": "1/26/2025",
    "country": "JP",
    "tournament": "Flagship(5-0)",
    "placement": "1st Place",
    "host": "Cardshop",
    "decklist": {
      "OP02-093": 1,
      "OP02-114": 4,
      "OP02-096": 3,
      "OP02-098": 2,
      "ST06-006": 4,
      "OP02-106": 4,
      "OP03-089": 4,
      "OP05-091": 4,
      "OP06-086": 4,
      "EB01-046": 4,
      "EB01-049": 2,
      "OP08-079": 3,
      "ST19-002": 4,
      "ST19-003": 4,
      "OP02-117": 4
    }
  },
  {
    "deck_name": "Red Green Smoker",
    "author": "Asura",
    "date": "1/26/2025",
    "country": "JP",
    "tournament": "Shop Event",
    "placement": "1st Place",
    "host": "Banquet Cup",
    "decklist": {
      "OP10-001": 1,
      "OP01-006": 4,
      "OP09-009": 4,
      "OP10-004": 4,
      "OP10-005": 4,
      "OP10-011": 4,
      "ST21-014": 3,
      "OP01-051": 4,
      "OP05-030": 4,
      "OP06-035": 4,
      "OP10-030": 4,
      "OP10-032": 4,
      "OP01-029": 1,
      "OP10-018": 4,
      "OP05-037": 1,
      "EB02-020": 1
    }
  },
  {
    "deck_name": "Issho",
    "author": "Murabito",
    "date": "1/26/2025",
    "country": "JP",
    "tournament": "SB(4-1)",
    "placement": "2nd Place",
    "host": "Cardshop",
    "decklist": {
      "OP04-020": 1,
      "OP02-114": 4,
      "OP02-096": 4,
      "OP02-098": 2,
      "OP02-099": 4,
      "ST06-006": 4,
      "ST06-008": 4,
      "OP02-106": 4,
      "OP04-083": 2,
      "OP04-089": 1,
      "OP05-091": 2,
      "OP06-086": 3,
      "EB01-046": 4,
      "EB01-049": 2,
      "EB02-044": 2,
      "ST19-002": 4,
      "OP06-035": 2,
      "OP02-117": 2
    }
  },
  {
    "deck_name": "Blue Doffy",
    "author": "AYAKANA_1124",
    "date": "1/26/2025",
    "country": "JP",
    "tournament": "Shop Event(8-0)",
    "placement": "1st Place",
    "host": "Oni CS",
    "decklist": {
      "OP01-060": 1,
      "ST03-005": 2,
      "OP01-070": 1,
      "OP01-077": 4,
      "OP02-054": 2,
      "OP03-044": 1,
      "OP06-047": 2,
      "EB01-023": 4,
      "OP07-040": 4,
      "OP07-045": 4,
      "OP07-046": 4,
      "OP08-047": 4,
      "ST17-002": 4,
      "ST17-003": 4,
      "ST17-004": 4,
      "ST17-005": 4,
      "OP07-057": 2
    }
  },
  {
    "deck_name": "Red Purple Luffy",
    "author": "Tsuusaji",
    "date": "1/26/2025",
    "country": "JP",
    "tournament": "SB",
    "placement": "1st Place",
    "host": "onehappy_tcg",
    "decklist": {
      "ST10-002": 1,
      "ST04-005": 3,
      "ST10-013": 4,
      "OP05-067": 4,
      "OP05-073": 2,
      "EB01-061": 4,
      "OP07-064": 4,
      "ST18-001": 4,
      "OP09-119": 4,
      "OP09-065": 2,
      "OP09-072": 2,
      "OP01-016": 4,
      "OP07-015": 2,
      "OP09-004": 3,
      "OP09-118": 1,
      "ST04-014": 2,
      "OP09-078": 4,
      "OP10-019": 1
    }
  },
  {
    "deck_name": "Green Purple Luffy",
    "author": "Sakanoko",
    "date": "1/26/2025",
    "country": "JP",
    "tournament": "Shop Event",
    "placement": "2nd Place",
    "host": "Kogiraf Cup",
    "decklist": {
      "EB02-010": 1,
      "OP05-067": 4,
      "EB02-035": 4,
      "EB02-037": 4,
      "EB02-061": 4,
      "OP07-064": 4,
      "ST18-001": 4,
      "ST18-004": 4,
      "OP02-041": 2,
      "EB01-014": 4,
      "EB02-017": 4,
      "OP03-072": 2,
      "OP05-076": 2,
      "EB02-041": 4,
      "OP09-078": 4
    }
  },
  {
    "deck_name": "Purple Luffy",
    "author": "Nishi",
    "date": "1/26/2025",
    "country": "JP",
    "tournament": "3v3(6-1)",
    "placement": "1st Place",
    "host": "Hacchi CS(93)",
    "decklist": {
      "OP05-060": 1,
      "ST10-010": 2,
      "OP05-070": 1,
      "OP05-074": 4,
      "OP06-076": 4,
      "OP07-064": 4,
      "OP08-069": 3,
      "ST18-001": 4,
      "ST18-002": 3,
      "ST18-003": 4,
      "ST18-004": 4,
      "ST18-005": 4,
      "OP09-119": 2,
      "OP09-065": 3,
      "OP09-069": 4,
      "OP09-078": 4
    }
  },
  {
    "deck_name": "Teach",
    "author": "R",
    "date": "1/26/2025",
    "country": "JP",
    "tournament": "3v3(7-0)",
    "placement": "1st Place",
    "host": "Hacchi CS(93)",
    "decklist": {
      "OP09-081": 1,
      "OP09-083": 4,
      "OP09-086": 4,
      "OP09-088": 2,
      "OP09-089": 4,
      "OP09-090": 4,
      "OP09-091": 2,
      "OP09-093": 4,
      "OP09-095": 4,
      "OP10-082": 4,
      "EB01-051": 4,
      "OP09-096": 4,
      "OP09-098": 3,
      "OP09-099": 4,
      "OP10-098": 3
    }
  },
  {
    "deck_name": "Teach",
    "author": "Domiziano",
    "date": "1/25/2025",
    "country": "Thailand",
    "tournament": "Flagship(6-0)",
    "placement": "1st Place",
    "host": "Cardshop",
    "decklist": {
      "OP09-081": 1,
      "OP09-083": 3,
      "OP09-086": 4,
      "OP09-088": 2,
      "OP09-089": 4,
      "OP09-090": 4,
      "OP09-091": 2,
      "OP09-093": 4,
      "OP09-095": 4,
      "OP10-082": 4,
      "OP10-085": 1,
      "OP10-086": 2,
      "EB01-051": 4,
      "OP09-096": 4,
      "OP09-098": 3,
      "OP09-099": 3,
      "OP10-098": 2
    }
  },
  {
    "deck_name": "Purple Luffy",
    "author": "Hirohiro",
    "date": "1/25/2025",
    "country": "JP",
    "tournament": "3v3(7-1)",
    "placement": "2nd Place",
    "host": "Hacchi CS(96)",
    "decklist": {
      "OP05-060": 1,
      "ST10-008": 2,
      "OP05-070": 2,
      "OP05-074": 4,
      "OP06-076": 4,
      "OP07-064": 4,
      "OP08-069": 2,
      "ST18-001": 4,
      "ST18-002": 4,
      "ST18-003": 4,
      "ST18-004": 4,
      "ST18-005": 4,
      "OP09-119": 2,
      "OP09-065": 2,
      "OP09-069": 4,
      "OP09-078": 4
    }
  },
  {
    "deck_name": "Boa Hancock",
    "author": "Moririn",
    "date": "1/25/2025",
    "country": "JP",
    "tournament": "3v3(6-2)",
    "placement": "1st Place",
    "host": "Corgi",
    "decklist": {
      "OP07-038": 1,
      "ST03-008": 4,
      "OP01-073": 4,
      "OP01-077": 2,
      "OP03-044": 4,
      "OP04-044": 3,
      "EB01-023": 4,
      "OP07-040": 3,
      "OP07-045": 4,
      "OP07-046": 4,
      "OP08-047": 4,
      "ST17-003": 3,
      "OP10-046": 3,
      "OP02-068": 1,
      "OP04-056": 4,
      "OP06-058": 3
    }
  },
  {
    "deck_name": "Boa Hancock",
    "author": "Piyochi",
    "date": "1/25/2025",
    "country": "JP",
    "tournament": "FLagship(5-0)",
    "placement": "1st Place",
    "host": "Cardshop",
    "decklist": {
      "OP07-038": 1,
      "ST03-005": 1,
      "ST03-008": 3,
      "OP01-073": 3,
      "OP01-070": 1,
      "OP01-077": 1,
      "OP03-044": 4,
      "OP04-044": 3,
      "OP07-040": 3,
      "OP07-045": 4,
      "OP07-046": 4,
      "OP08-047": 4,
      "ST17-002": 4,
      "ST17-003": 4,
      "OP10-046": 3,
      "OP03-057": 2,
      "OP04-056": 4,
      "OP06-058": 2
    }
  },
  {
    "deck_name": "Red Purple Luffy",
    "author": "Salmon_op",
    "date": "1/25/2025",
    "country": "JP",
    "tournament": "Shop Event(6-0)",
    "placement": "1st Place",
    "host": "Cardshop",
    "decklist": {
      "ST10-002": 1,
      "ST10-013": 4,
      "OP05-067": 4,
      "OP05-070": 1,
      "OP05-073": 4,
      "EB01-061": 4,
      "EB02-036": 4,
      "EB02-061": 3,
      "OP07-064": 4,
      "ST18-001": 3,
      "ST18-002": 4,
      "OP09-119": 3,
      "OP01-016": 4,
      "OP09-004": 3,
      "EB02-041": 1,
      "OP09-078": 4
    }
  },
  {
    "deck_name": "Purple Luffy",
    "author": "Tenten",
    "date": "1/25/2025",
    "country": "JP",
    "tournament": "3v3(7-1)",
    "placement": "1st Place",
    "host": "Hacchi CS(96)",
    "decklist": {
      "OP05-060": 1,
      "ST10-008": 4,
      "OP05-074": 4,
      "OP06-076": 4,
      "OP07-064": 4,
      "OP08-069": 2,
      "ST18-001": 4,
      "ST18-002": 4,
      "ST18-003": 4,
      "ST18-004": 4,
      "ST18-005": 4,
      "OP09-119": 2,
      "OP09-065": 2,
      "OP09-069": 4,
      "OP09-078": 4
    }
  },
  {
    "deck_name": "Yellow Enel",
    "author": "Nigou",
    "date": "1/25/2025",
    "country": "JP",
    "tournament": "3v3(5-1)",
    "placement": "Top-4",
    "host": "Hacchi CS",
    "decklist": {
      "OP05-098": 1,
      "OP03-123": 4,
      "OP04-100": 4,
      "OP04-112": 4,
      "OP05-102": 4,
      "EB01-056": 4,
      "EB01-057": 4,
      "EB02-052": 4,
      "EB02-054": 3,
      "OP07-119": 1,
      "OP08-106": 2,
      "OP10-114": 4,
      "OP06-115": 4,
      "EB01-059": 4,
      "OP10-116": 4
    }
  },
  {
    "deck_name": "Yellow Enel",
    "author": "Piroshiki",
    "date": "1/25/2025",
    "country": "JP",
    "tournament": "SB",
    "placement": "1st Place",
    "host": "Takuro Cup(14)",
    "decklist": {
      "OP05-098": 1,
      "OP03-123": 4,
      "OP04-100": 3,
      "OP04-112": 2,
      "OP06-101": 4,
      "OP06-104": 4,
      "EB01-057": 4,
      "EB02-052": 4,
      "OP07-107": 3,
      "OP07-119": 4,
      "OP08-106": 4,
      "OP10-114": 4,
      "OP06-115": 4,
      "EB01-059": 4,
      "EB02-058": 2
    }
  },
  {
    "deck_name": "Yellow Enel",
    "author": "Suko",
    "date": "1/25/2025",
    "country": "JP",
    "tournament": "3v3(6-2)",
    "placement": "1st Place",
    "host": "Stew Cup",
    "decklist": {
      "OP05-098": 1,
      "OP03-116": 4,
      "OP03-123": 4,
      "OP04-112": 4,
      "EB01-056": 4,
      "EB01-057": 4,
      "EB02-052": 3,
      "OP07-107": 4,
      "OP07-119": 3,
      "OP08-106": 4,
      "OP10-114": 4,
      "OP06-115": 4,
      "EB01-059": 4,
      "OP10-116": 4
    }
  },
  {
    "deck_name": "Vegapunk",
    "author": "Hide Tanaka",
    "date": "1/25/2025",
    "country": "JP",
    "tournament": "SB",
    "placement": "1st Place",
    "host": "HBST(16)",
    "decklist": {
      "OP07-097": 1,
      "ST13-011": 4,
      "EB02-056": 4,
      "OP07-100": 4,
      "OP07-101": 4,
      "OP07-105": 4,
      "OP07-107": 4,
      "OP07-109": 4,
      "OP07-110": 4,
      "OP07-111": 4,
      "OP07-098": 4,
      "OP08-106": 4,
      "OP08-112": 2,
      "EB01-059": 2,
      "OP07-115": 2
    }
  },
  {
    "deck_name": "Teach",
    "author": "Ives Rementina",
    "date": "1/25/2025",
    "country": "PH",
    "tournament": "Flagship",
    "placement": "1st Place",
    "host": "Top Deck Games",
    "decklist": {
      "OP09-081": 1,
      "OP09-083": 4,
      "OP09-086": 4,
      "OP09-088": 3,
      "OP09-089": 4,
      "OP09-090": 4,
      "OP09-091": 2,
      "OP09-093": 4,
      "OP09-095": 4,
      "OP10-082": 4,
      "EB01-051": 4,
      "OP09-096": 4,
      "OP09-098": 3,
      "OP09-099": 4,
      "OP10-098": 2
    }
  },
  {
    "deck_name": "Teach",
    "author": "Nekomaru",
    "date": "1/25/2025",
    "country": "JP",
    "tournament": "3v3(5-0)",
    "placement": "NA",
    "host": "Memories Cup",
    "decklist": {
      "OP09-081": 1,
      "OP09-083": 4,
      "OP09-086": 4,
      "OP09-088": 2,
      "OP09-089": 4,
      "OP09-090": 4,
      "OP09-091": 3,
      "OP09-093": 4,
      "OP09-095": 4,
      "OP10-082": 4,
      "EB01-051": 4,
      "OP09-096": 4,
      "OP09-098": 3,
      "OP09-099": 4,
      "OP10-098": 2
    }
  },
  {
    "deck_name": "Teach",
    "author": "Potaka",
    "date": "1/25/2025",
    "country": "JP",
    "tournament": "3v3(7-0)",
    "placement": "Top-4",
    "host": "Luminous CS",
    "decklist": {
      "OP09-081": 1,
      "OP09-083": 4,
      "OP09-086": 4,
      "OP09-088": 2,
      "OP09-089": 4,
      "OP09-090": 4,
      "OP09-091": 3,
      "OP09-093": 4,
      "OP09-095": 4,
      "OP10-082": 4,
      "EB01-051": 4,
      "OP09-096": 4,
      "OP09-098": 3,
      "OP09-099": 4,
      "OP10-098": 2
    }
  },
  {
    "deck_name": "Smoker",
    "author": "Zato",
    "date": "1/25/2025",
    "country": "JP",
    "tournament": "SB(4-0)",
    "placement": "1st Place",
    "host": "Cardshop",
    "decklist": {
      "OP02-093": 1,
      "OP02-114": 2,
      "OP02-096": 3,
      "ST06-004": 1,
      "ST06-006": 4,
      "ST06-008": 1,
      "ST06-010": 1,
      "OP02-106": 4,
      "OP03-089": 3,
      "OP05-091": 4,
      "OP06-086": 4,
      "EB01-046": 4,
      "EB01-049": 3,
      "EB02-044": 2,
      "OP08-079": 2,
      "ST19-002": 4,
      "ST19-003": 4,
      "OP02-117": 4
    }
  }
]